{"color":"Color","director_name":"James Cameron","num_critic_for_reviews":723,"duration":178,"director_facebook_likes":0,"actor_3_facebook_likes":855,"actor_2_name":"Joel David Moore","actor_1_facebook_likes":1000,"gross":760505847,"genres":"Action|Adventure|Fantasy|Sci-Fi","actor_1_name":"CCH Pounder","movie_title":"Avatar ","num_voted_users":886204,"cast_total_facebook_likes":4834,"actor_3_name":"Wes Studi","facenumber_in_poster":0,"plot_keywords":"avatar|future|marine|native|paraplegic","movie_imdb_link":"http://www.imdb.com/title/tt0499549/?ref_=fn_tt_tt_1","num_user_for_reviews":3054,"language":"English","country":"USA","content_rating":"PG-13","budget":237000000,"title_year":2009,"actor_2_facebook_likes":936,"imdb_score":7.9,"aspect_ratio":1.78,"movie_facebook_likes":33000}
{"color":"Color","director_name":"Gore Verbinski","num_critic_for_reviews":302,"duration":169,"director_facebook_likes":563,"actor_3_facebook_likes":1000,"actor_2_name":"Orlando Bloom","actor_1_facebook_likes":40000,"gross":309404152,"genres":"Action|Adventure|Fantasy","actor_1_name":"Johnny Depp","movie_title":"Pirates of the Caribbean: At World's End ","num_voted_users":471220,"cast_total_facebook_likes":48350,"actor_3_name":"Jack Davenport","facenumber_in_poster":0,"plot_keywords":"goddess|marriage ceremony|marriage proposal|pirate|singapore","movie_imdb_link":"http://www.imdb.com/title/tt0449088/?ref_=fn_tt_tt_1","num_user_for_reviews":1238,"language":"English","country":"USA","content_rating":"PG-13","budget":300000000,"title_year":2007,"actor_2_facebook_likes":5000,"imdb_score":7.1,"aspect_ratio":2.35,"movie_facebook_likes":0}
{"color":"Color","director_name":"Sam Mendes","num_critic_for_reviews":602,"duration":148,"director_facebook_likes":0,"actor_3_facebook_likes":161,"actor_2_name":"Rory Kinnear","actor_1_facebook_likes":11000,"gross":200074175,"genres":"Action|Adventure|Thriller","actor_1_name":"Christoph Waltz","movie_title":"Spectre ","num_voted_users":275868,"cast_total_facebook_likes":11700,"actor_3_name":"Stephanie Sigman","facenumber_in_poster":1,"plot_keywords":"bomb|espionage|sequel|spy|terrorist","movie_imdb_link":"http://www.imdb.com/title/tt2379713/?ref_=fn_tt_tt_1","num_user_for_reviews":994,"language":"English","country":"UK","content_rating":"PG-13","budget":245000000,"title_year":2015,"actor_2_facebook_likes":393,"imdb_score":6.8,"aspect_ratio":2.35,"movie_facebook_likes":85000}
{"color":"Color","director_name":"Christopher Nolan","num_critic_for_reviews":813,"duration":164,"director_facebook_likes":22000,"actor_3_facebook_likes":23000,"actor_2_name":"Christian Bale","actor_1_facebook_likes":27000,"gross":448130642,"genres":"Action|Thriller","actor_1_name":"Tom Hardy","movie_title":"The Dark Knight Rises ","num_voted_users":1144337,"cast_total_facebook_likes":106759,"actor_3_name":"Joseph Gordon-Levitt","facenumber_in_poster":0,"plot_keywords":"deception|imprisonment|lawlessness|police officer|terrorist plot","movie_imdb_link":"http://www.imdb.com/title/tt1345836/?ref_=fn_tt_tt_1","num_user_for_reviews":2701,"language":"English","country":"USA","content_rating":"PG-13","budget":250000000,"title_year":2012,"actor_2_facebook_likes":23000,"imdb_score":8.5,"aspect_ratio":2.35,"movie_facebook_likes":164000}
{"color":null,"director_name":"Doug Walker","num_critic_for_reviews":null,"duration":null,"director_facebook_likes":131,"actor_3_facebook_likes":null,"actor_2_name":"Rob Walker","actor_1_facebook_likes":131,"gross":null,"genres":"Documentary","actor_1_name":"Doug Walker","movie_title":"Star Wars: Episode VII - The Force Awakens             ","num_voted_users":8,"cast_total_facebook_likes":143,"actor_3_name":null,"facenumber_in_poster":0,"plot_keywords":null,"movie_imdb_link":"http://www.imdb.com/title/tt5289954/?ref_=fn_tt_tt_1","num_user_for_reviews":null,"language":null,"country":null,"content_rating":null,"budget":null,"title_year":null,"actor_2_facebook_likes":12,"imdb_score":7.1,"aspect_ratio":null,"movie_facebook_likes":0}
{"color":"Color","director_name":"Andrew Stanton","num_critic_for_reviews":462,"duration":132,"director_facebook_likes":475,"actor_3_facebook_likes":530,"actor_2_name":"Samantha Morton","actor_1_facebook_likes":640,"gross":73058679,"genres":"Action|Adventure|Sci-Fi","actor_1_name":"Daryl Sabara","movie_title":"John Carter ","num_voted_users":212204,"cast_total_facebook_likes":1873,"actor_3_name":"Polly Walker","facenumber_in_poster":1,"plot_keywords":"alien|american civil war|male nipple|mars|princess","movie_imdb_link":"http://www.imdb.com/title/tt0401729/?ref_=fn_tt_tt_1","num_user_for_reviews":738,"language":"English","country":"USA","content_rating":"PG-13","budget":263700000,"title_year":2012,"actor_2_facebook_likes":632,"imdb_score":6.6,"aspect_ratio":2.35,"movie_facebook_likes":24000}
{"color":"Color","director_name":"Sam Raimi","num_critic_for_reviews":392,"duration":156,"director_facebook_likes":0,"actor_3_facebook_likes":4000,"actor_2_name":"James Franco","actor_1_facebook_likes":24000,"gross":336530303,"genres":"Action|Adventure|Romance","actor_1_name":"J.K. Simmons","movie_title":"Spider-Man 3 ","num_voted_users":383056,"cast_total_facebook_likes":46055,"actor_3_name":"Kirsten Dunst","facenumber_in_poster":0,"plot_keywords":"sandman|spider man|symbiote|venom|villain","movie_imdb_link":"http://www.imdb.com/title/tt0413300/?ref_=fn_tt_tt_1","num_user_for_reviews":1902,"language":"English","country":"USA","content_rating":"PG-13","budget":258000000,"title_year":2007,"actor_2_facebook_likes":11000,"imdb_score":6.2,"aspect_ratio":2.35,"movie_facebook_likes":0}
{"color":"Color","director_name":"Nathan Greno","num_critic_for_reviews":324,"duration":100,"director_facebook_likes":15,"actor_3_facebook_likes":284,"actor_2_name":"Donna Murphy","actor_1_facebook_likes":799,"gross":200807262,"genres":"Adventure|Animation|Comedy|Family|Fantasy|Musical|Romance","actor_1_name":"Brad Garrett","movie_title":"Tangled ","num_voted_users":294810,"cast_total_facebook_likes":2036,"actor_3_name":"M.C. Gainey","facenumber_in_poster":1,"plot_keywords":"17th century|based on fairy tale|disney|flower|tower","movie_imdb_link":"http://www.imdb.com/title/tt0398286/?ref_=fn_tt_tt_1","num_user_for_reviews":387,"language":"English","country":"USA","content_rating":"PG","budget":260000000,"title_year":2010,"actor_2_facebook_likes":553,"imdb_score":7.8,"aspect_ratio":1.85,"movie_facebook_likes":29000}
{"color":"Color","director_name":"Joss Whedon","num_critic_for_reviews":635,"duration":141,"director_facebook_likes":0,"actor_3_facebook_likes":19000,"actor_2_name":"Robert Downey Jr.","actor_1_facebook_likes":26000,"gross":458991599,"genres":"Action|Adventure|Sci-Fi","actor_1_name":"Chris Hemsworth","movie_title":"Avengers: Age of Ultron ","num_voted_users":462669,"cast_total_facebook_likes":92000,"actor_3_name":"Scarlett Johansson","facenumber_in_poster":4,"plot_keywords":"artificial intelligence|based on comic book|captain america|marvel cinematic universe|superhero","movie_imdb_link":"http://www.imdb.com/title/tt2395427/?ref_=fn_tt_tt_1","num_user_for_reviews":1117,"language":"English","country":"USA","content_rating":"PG-13","budget":250000000,"title_year":2015,"actor_2_facebook_likes":21000,"imdb_score":7.5,"aspect_ratio":2.35,"movie_facebook_likes":118000}
{"color":"Color","director_name":"David Yates","num_critic_for_reviews":375,"duration":153,"director_facebook_likes":282,"actor_3_facebook_likes":10000,"actor_2_name":"Daniel Radcliffe","actor_1_facebook_likes":25000,"gross":301956980,"genres":"Adventure|Family|Fantasy|Mystery","actor_1_name":"Alan Rickman","movie_title":"Harry Potter and the Half-Blood Prince ","num_voted_users":321795,"cast_total_facebook_likes":58753,"actor_3_name":"Rupert Grint","facenumber_in_poster":3,"plot_keywords":"blood|book|love|potion|professor","movie_imdb_link":"http://www.imdb.com/title/tt0417741/?ref_=fn_tt_tt_1","num_user_for_reviews":973,"language":"English","country":"UK","content_rating":"PG","budget":250000000,"title_year":2009,"actor_2_facebook_likes":11000,"imdb_score":7.5,"aspect_ratio":2.35,"movie_facebook_likes":10000}
{"color":"Color","director_name":"Zack Snyder","num_critic_for_reviews":673,"duration":183,"director_facebook_likes":0,"actor_3_facebook_likes":2000,"actor_2_name":"Lauren Cohan","actor_1_facebook_likes":15000,"gross":330249062,"genres":"Action|Adventure|Sci-Fi","actor_1_name":"Henry Cavill","movie_title":"Batman v Superman: Dawn of Justice ","num_voted_users":371639,"cast_total_facebook_likes":24450,"actor_3_name":"Alan D. Purwin","facenumber_in_poster":0,"plot_keywords":"based on comic book|batman|sequel to a reboot|superhero|superman","movie_imdb_link":"http://www.imdb.com/title/tt2975590/?ref_=fn_tt_tt_1","num_user_for_reviews":3018,"language":"English","country":"USA","content_rating":"PG-13","budget":250000000,"title_year":2016,"actor_2_facebook_likes":4000,"imdb_score":6.9,"aspect_ratio":2.35,"movie_facebook_likes":197000}
{"color":"Color","director_name":"Bryan Singer","num_critic_for_reviews":434,"duration":169,"director_facebook_likes":0,"actor_3_facebook_likes":903,"actor_2_name":"Marlon Brando","actor_1_facebook_likes":18000,"gross":200069408,"genres":"Action|Adventure|Sci-Fi","actor_1_name":"Kevin Spacey","movie_title":"Superman Returns ","num_voted_users":240396,"cast_total_facebook_likes":29991,"actor_3_name":"Frank Langella","facenumber_in_poster":0,"plot_keywords":"crystal|epic|lex luthor|lois lane|return to earth","movie_imdb_link":"http://www.imdb.com/title/tt0348150/?ref_=fn_tt_tt_1","num_user_for_reviews":2367,"language":"English","country":"USA","content_rating":"PG-13","budget":209000000,"title_year":2006,"actor_2_facebook_likes":10000,"imdb_score":6.1,"aspect_ratio":2.35,"movie_facebook_likes":0}
{"color":"Color","director_name":"Marc Forster","num_critic_for_reviews":403,"duration":106,"director_facebook_likes":395,"actor_3_facebook_likes":393,"actor_2_name":"Mathieu Amalric","actor_1_facebook_likes":451,"gross":168368427,"genres":"Action|Adventure","actor_1_name":"Giancarlo Giannini","movie_title":"Quantum of Solace ","num_voted_users":330784,"cast_total_facebook_likes":2023,"actor_3_name":"Rory Kinnear","facenumber_in_poster":1,"plot_keywords":"action hero|attempted rape|bond girl|official james bond series|revenge","movie_imdb_link":"http://www.imdb.com/title/tt0830515/?ref_=fn_tt_tt_1","num_user_for_reviews":1243,"language":"English","country":"UK","content_rating":"PG-13","budget":200000000,"title_year":2008,"actor_2_facebook_likes":412,"imdb_score":6.7,"aspect_ratio":2.35,"movie_facebook_likes":0}
{"color":"Color","director_name":"Gore Verbinski","num_critic_for_reviews":313,"duration":151,"director_facebook_likes":563,"actor_3_facebook_likes":1000,"actor_2_name":"Orlando Bloom","actor_1_facebook_likes":40000,"gross":423032628,"genres":"Action|Adventure|Fantasy","actor_1_name":"Johnny Depp","movie_title":"Pirates of the Caribbean: Dead Man's Chest ","num_voted_users":522040,"cast_total_facebook_likes":48486,"actor_3_name":"Jack Davenport","facenumber_in_poster":2,"plot_keywords":"box office hit|giant squid|heart|liar's dice|monster","movie_imdb_link":"http://www.imdb.com/title/tt0383574/?ref_=fn_tt_tt_1","num_user_for_reviews":1832,"language":"English","country":"USA","content_rating":"PG-13","budget":225000000,"title_year":2006,"actor_2_facebook_likes":5000,"imdb_score":7.3,"aspect_ratio":2.35,"movie_facebook_likes":5000}
{"color":"Color","director_name":"Gore Verbinski","num_critic_for_reviews":450,"duration":150,"director_facebook_likes":563,"actor_3_facebook_likes":1000,"actor_2_name":"Ruth Wilson","actor_1_facebook_likes":40000,"gross":89289910,"genres":"Action|Adventure|Western","actor_1_name":"Johnny Depp","movie_title":"The Lone Ranger ","num_voted_users":181792,"cast_total_facebook_likes":45757,"actor_3_name":"Tom Wilkinson","facenumber_in_poster":1,"plot_keywords":"horse|outlaw|texas|texas ranger|train","movie_imdb_link":"http://www.imdb.com/title/tt1210819/?ref_=fn_tt_tt_1","num_user_for_reviews":711,"language":"English","country":"USA","content_rating":"PG-13","budget":215000000,"title_year":2013,"actor_2_facebook_likes":2000,"imdb_score":6.5,"aspect_ratio":2.35,"movie_facebook_likes":48000}
{"color":"Color","director_name":"Zack Snyder","num_critic_for_reviews":733,"duration":143,"director_facebook_likes":0,"actor_3_facebook_likes":748,"actor_2_name":"Christopher Meloni","actor_1_facebook_likes":15000,"gross":291021565,"genres":"Action|Adventure|Fantasy|Sci-Fi","actor_1_name":"Henry Cavill","movie_title":"Man of Steel ","num_voted_users":548573,"cast_total_facebook_likes":20495,"actor_3_name":"Harry Lennix","facenumber_in_poster":0,"plot_keywords":"based on comic book|british actor playing american character|final battle|origin of hero|reboot","movie_imdb_link":"http://www.imdb.com/title/tt0770828/?ref_=fn_tt_tt_1","num_user_for_reviews":2536,"language":"English","country":"USA","content_rating":"PG-13","budget":225000000,"title_year":2013,"actor_2_facebook_likes":3000,"imdb_score":7.2,"aspect_ratio":2.35,"movie_facebook_likes":118000}
{"color":"Color","director_name":"Andrew Adamson","num_critic_for_reviews":258,"duration":150,"director_facebook_likes":80,"actor_3_facebook_likes":201,"actor_2_name":"Pierfrancesco Favino","actor_1_facebook_likes":22000,"gross":141614023,"genres":"Action|Adventure|Family|Fantasy","actor_1_name":"Peter Dinklage","movie_title":"The Chronicles of Narnia: Prince Caspian ","num_voted_users":149922,"cast_total_facebook_likes":22697,"actor_3_name":"Damián Alcázar","facenumber_in_poster":4,"plot_keywords":"brother brother relationship|brother sister relationship|good versus evil|king|narnia","movie_imdb_link":"http://www.imdb.com/title/tt0499448/?ref_=fn_tt_tt_1","num_user_for_reviews":438,"language":"English","country":"USA","content_rating":"PG","budget":225000000,"title_year":2008,"actor_2_facebook_likes":216,"imdb_score":6.6,"aspect_ratio":2.35,"movie_facebook_likes":0}
{"color":"Color","director_name":"Joss Whedon","num_critic_for_reviews":703,"duration":173,"director_facebook_likes":0,"actor_3_facebook_likes":19000,"actor_2_name":"Robert Downey Jr.","actor_1_facebook_likes":26000,"gross":623279547,"genres":"Action|Adventure|Sci-Fi","actor_1_name":"Chris Hemsworth","movie_title":"The Avengers ","num_voted_users":995415,"cast_total_facebook_likes":87697,"actor_3_name":"Scarlett Johansson","facenumber_in_poster":3,"plot_keywords":"alien invasion|assassin|battle|iron man|soldier","movie_imdb_link":"http://www.imdb.com/title/tt0848228/?ref_=fn_tt_tt_1","num_user_for_reviews":1722,"language":"English","country":"USA","content_rating":"PG-13","budget":220000000,"title_year":2012,"actor_2_facebook_likes":21000,"imdb_score":8.1,"aspect_ratio":1.85,"movie_facebook_likes":123000}
{"color":"Color","director_name":"Rob Marshall","num_critic_for_reviews":448,"duration":136,"director_facebook_likes":252,"actor_3_facebook_likes":1000,"actor_2_name":"Sam Claflin","actor_1_facebook_likes":40000,"gross":241063875,"genres":"Action|Adventure|Fantasy","actor_1_name":"Johnny Depp","movie_title":"Pirates of the Caribbean: On Stranger Tides ","num_voted_users":370704,"cast_total_facebook_likes":54083,"actor_3_name":"Stephen Graham","facenumber_in_poster":4,"plot_keywords":"blackbeard|captain|pirate|revenge|soldier","movie_imdb_link":"http://www.imdb.com/title/tt1298650/?ref_=fn_tt_tt_1","num_user_for_reviews":484,"language":"English","country":"USA","content_rating":"PG-13","budget":250000000,"title_year":2011,"actor_2_facebook_likes":11000,"imdb_score":6.7,"aspect_ratio":2.35,"movie_facebook_likes":58000}
{"color":"Color","director_name":"Barry Sonnenfeld","num_critic_for_reviews":451,"duration":106,"director_facebook_likes":188,"actor_3_facebook_likes":718,"actor_2_name":"Michael Stuhlbarg","actor_1_facebook_likes":10000,"gross":179020854,"genres":"Action|Adventure|Comedy|Family|Fantasy|Sci-Fi","actor_1_name":"Will Smith","movie_title":"Men in Black 3 ","num_voted_users":268154,"cast_total_facebook_likes":12572,"actor_3_name":"Nicole Scherzinger","facenumber_in_poster":1,"plot_keywords":"alien|criminal|m.i.b.|maximum security prison|prison","movie_imdb_link":"http://www.imdb.com/title/tt1409024/?ref_=fn_tt_tt_1","num_user_for_reviews":341,"language":"English","country":"USA","content_rating":"PG-13","budget":225000000,"title_year":2012,"actor_2_facebook_likes":816,"imdb_score":6.8,"aspect_ratio":1.85,"movie_facebook_likes":40000}
